prime_evals/__init__.py
prime_evals/evals.py
prime_evals/exceptions.py
prime_evals/models.py
prime_evals/py.typed
prime_evals/core/__init__.py
prime_evals/core/client.py
prime_evals/core/config.py
prime_evals-0.1.10.dist-info/METADATA
prime_evals-0.1.10.dist-info/WHEEL
prime_evals-0.1.10.dist-info/RECORD
