Metadata-Version: 2.4
Name: prime-evals
Version: 0.1.10
Summary: Prime Intellect Evals SDK - Push and manage evaluations
Project-URL: Homepage, https://github.com/PrimeIntellect-ai/prime-cli
Project-URL: Documentation, https://github.com/PrimeIntellect-ai/prime-cli/tree/main/packages/prime-evals
Project-URL: Repository, https://github.com/PrimeIntellect-ai/prime-cli.git
Author-email: Prime Intellect <contact@primeintellect.ai>
License: MIT
Keywords: evals,evaluations
Classifier: Development Status :: 4 - Beta
Classifier: Intended Audience :: Developers
Classifier: License :: OSI Approved :: MIT License
Classifier: Operating System :: OS Independent
Classifier: Programming Language :: Python :: 3
Classifier: Programming Language :: Python :: 3.10
Classifier: Programming Language :: Python :: 3.11
Classifier: Programming Language :: Python :: 3.12
Classifier: Topic :: Scientific/Engineering :: Artificial Intelligence
Classifier: Topic :: Software Development :: Libraries :: Python Modules
Requires-Python: >=3.10
Requires-Dist: httpx>=0.25.0
Requires-Dist: pydantic>=2.0.0
Requires-Dist: tenacity>=9.1.2
Provides-Extra: dev
Requires-Dist: pytest>=7.0.0; extra == 'dev'
Requires-Dist: ruff>=0.13.1; extra == 'dev'
